firstimpression/__init__.py
firstimpression/constants.py
firstimpression/api/__init__.py
firstimpression/api/request.py
firstimpression/api/amber_alert/__init__.py
firstimpression/api/ams_airport/__init__.py
firstimpression/api/bbc/__init__.py
firstimpression/api/chuck_norris/__init__.py
firstimpression/api/countdown/__init__.py
firstimpression/api/default/__init__.py
firstimpression/api/ehv_airport/__init__.py
firstimpression/api/facebook/__init__.py
firstimpression/api/google_trends/__init__.py
firstimpression/api/insta/__init__.py
firstimpression/api/interia/__init__.py
firstimpression/api/ns/__init__.py
firstimpression/api/nu_nl/__init__.py
firstimpression/api/solaredge/__init__.py
firstimpression/api/songkick/__init__.py
firstimpression/api/traffic/__init__.py
firstimpression/api/twitter/__init__.py
firstimpression/api/weather/__init__.py
firstimpression/api/world_times/__init__.py
firstimpression/file/__init__.py
firstimpression/json/__init__.py
firstimpression/local/__init__.py
firstimpression/placeholder/__init__.py
firstimpression/rss/__init__.py
firstimpression/scala/__init__.py
firstimpression/text/__init__.py
firstimpression/time/__init__.py
firstimpression/whitelabel/__init__.py
firstimpression/xml/__init__.py
firstimpression-3.0.16.dist-info/LICENSE
firstimpression-3.0.16.dist-info/METADATA
firstimpression-3.0.16.dist-info/WHEEL
firstimpression-3.0.16.dist-info/top_level.txt
firstimpression-3.0.16.dist-info/RECORD
